dataflowutil/config/__int__.py
dataflowutil/config/extra_var.py
dataflowutil/libs/__int__.py
dataflowutil/libs/app_struct.py
dataflowutil/libs/data_check.py
dataflowutil/libs/load_bucket.py
dataflowutil/libs/load_connection.py
dataflowutil/libs/load_data.py
dataflowutil/libs/load_interface.py
dataflowutil/libs/load_processing.py
dataflowutil/libs/load_report.py
dataflowutil/libs/load_spreadsheets.py
dataflowutil/libs/upload_data.py
dataflowutil-0.0.11.dist-info/METADATA
dataflowutil-0.0.11.dist-info/WHEEL
dataflowutil-0.0.11.dist-info/top_level.txt
dataflowutil-0.0.11.dist-info/RECORD
