Metadata-Version: 2.1
Name: dataflowutil
Version: 0.0.11
Author: Felipe Ardila (WorldArd)
Requires-Dist: pandas ==1.5.0
Requires-Dist: pandas-gbq ==0.19.2
Requires-Dist: google-cloud-storage ==2.10.0
Requires-Dist: openpyxl ==3.1.2
Requires-Dist: fsspec ==2023.6.0
Requires-Dist: gcsfs ==2023.6.0
Requires-Dist: levenshtein ==0.21.1
Requires-Dist: google-api-python-client ==2.100.0
Requires-Dist: ipywidgets ==8.1.1
Requires-Dist: google-cloud-bigquery-datatransfer ==3.12.1
Requires-Dist: dash ==2.14.0
Requires-Dist: dash-bootstrap-components ==1.5.0
Requires-Dist: PyYAML ==6.0.1
